snorer/__init__.py
snorer/constants.py
snorer/geometry.py
snorer/halo.py
snorer/kinematics.py
snorer/params.py
snorer/snorerMain.py
snorer/sysmsg.py
snorer/utils.py
snorer-2.1.0.dist-info/licenses/LICENSE
snorer-2.1.0.dist-info/METADATA
snorer-2.1.0.dist-info/WHEEL
snorer-2.1.0.dist-info/top_level.txt
snorer-2.1.0.dist-info/RECORD
