Metadata-Version: 2.4
Name: snorer
Version: 2.1.0
Summary: This package evaluates the time-of-flight signatures of boosted dark matter due to supernova neutrinos from our Milky Way
Author-email: Yen-Hsun Lin <yenhsun@phys.ncku.edu.tw>
License: GNU GENERAL PUBLIC LICENSE
Project-URL: Homepage, https://github.com/yenhsunlin/snorer
Requires-Python: >=3.8
License-File: LICENSE
Requires-Dist: numpy>=1.20.0
Requires-Dist: scipy>=1.10.0
Requires-Dist: vegas>=6.0.1
Requires-Dist: astropy>=6.0.0
Dynamic: license-file
